{"description":"should save CDB as template|VFK-TC-214","passed":true,"pending":false,"os":"Windows NT","instanceId":19784,"browser":{"name":"chrome","version":"75.0.3770.142"},"message":"Passed.","trace":"","browserLogs":[{"level":"SEVERE","message":"https://test.fieldbuilder.ix3.com/fieldbuilder/static#/project/5b8668bfe22e8203b383237f/field - Failed to load resource: the server responded with a status of 403 ()","timestamp":1565611331392,"type":""},{"level":"SEVERE","message":"https://test.fieldbuilder.ix3.com/fieldbuilder/ - Failed to load resource: the server responded with a status of 403 ()","timestamp":1565611362151,"type":""}],"screenShotFile":"images\\00dd00d6-00f1-00c2-00b2-001900480024.png","timestamp":1565611328322,"duration":33877}
